[
  {
    "english": "thunder",
    "senses": [
      { "gloss": "noun", "members": [7088] },
      { "gloss": "verb", "members": [7523] }
    ]
  },
  {
    "english": "vertical",
    "senses": [
      { "gloss": "", "members": [7092, 8071] }
    ]
  },
  {
    "english": "grid, lattice, bars",
    "senses": [
      { "gloss": "bars, grating", "members": [7122] },
      { "gloss": "line grid", "members": [8176] }
    ]
  },
  {
    "english": "anniversary",
    "senses": [
      { "gloss": "yearly date", "members": [7164] },
      { "gloss": "milestone jubilee", "members": [7567] }
    ]
  },
  {
    "english": "delicious",
    "senses": [
      { "gloss": "", "members": [7193, 7644] }
    ]
  },
  {
    "english": "juice",
    "senses": [
      { "gloss": "cordial, concentrate", "members": [7257] },
      { "gloss": "fresh juice", "members": [7479] }
    ]
  },
  {
    "english": "stick, cane",
    "senses": [
      { "gloss": "walking cane", "members": [7262] },
      { "gloss": "twig, stick", "members": [7383] },
      { "gloss": "to cling", "members": [8145] }
    ]
  },
  {
    "english": "cancel, call off",
    "senses": [
      { "gloss": "", "members": [7285, 7381] }
    ]
  },
  {
    "english": "vein, blood vessel",
    "senses": [
      { "gloss": "", "members": [7889, 7624] }
    ]
  },
  {
    "english": "consult",
    "senses": [
      { "gloss": "", "members": [7302, 7572] }
    ]
  },
  {
    "english": "injustice",
    "senses": [
      { "gloss": "", "members": [7311, 7641] }
    ]
  },
  {
    "english": "collision, crash",
    "senses": [
      { "gloss": "", "members": [7333, 7365, 7704] }
    ]
  },
  {
    "english": "fame",
    "senses": [
      { "gloss": "renown", "members": [7347] },
      { "gloss": "celebrity, person", "members": [8307] }
    ]
  },
  {
    "english": "substitute, temp",
    "senses": [
      { "gloss": "stand-in worker", "members": [7387] },
      { "gloss": "replacement thing", "members": [7750] }
    ]
  },
  {
    "english": "bucket",
    "senses": [
      { "gloss": "", "members": [7412, 8093] }
    ]
  },
  {
    "english": "hut, cabin",
    "senses": [
      { "gloss": "", "members": [7441, 7615] }
    ]
  },
  {
    "english": "noble, of noble birth",
    "senses": [
      { "gloss": "aristocratic", "members": [7461] },
      { "gloss": "noble in character", "members": [7847, 8010] }
    ]
  },
  {
    "english": "steak, beefsteak",
    "senses": [
      { "gloss": "steak, patty", "members": [7470] },
      { "gloss": "roast", "members": [8014] }
    ]
  },
  {
    "english": "cabin, cab",
    "senses": [
      { "gloss": "", "members": [7501, 8230] }
    ]
  },
  {
    "english": "herd",
    "senses": [
      { "gloss": "to herd", "members": [7589] },
      { "gloss": "group of animals", "members": [7631] }
    ]
  },
  {
    "english": "beam",
    "senses": [
      { "gloss": "", "members": [7618, 8394] }
    ]
  },
  {
    "english": "orange",
    "senses": [
      { "gloss": "the fruit", "members": [7700] },
      { "gloss": "the color", "members": [8101] }
    ]
  },
  {
    "english": "orbit",
    "senses": [
      { "gloss": "orbital path", "members": [7715] },
      { "gloss": "circuit, revolution", "members": [7730] }
    ]
  },
  {
    "english": "seal",
    "senses": [
      { "gloss": "stamp, sigil", "members": [7721] },
      { "gloss": "to seal shut", "members": [8016] }
    ]
  },
  {
    "english": "realization, fulfilment",
    "senses": [
      { "gloss": "", "members": [7737, 8241] }
    ]
  },
  {
    "english": "animation",
    "senses": [
      { "gloss": "", "members": [7757, 8245] }
    ]
  },
  {
    "english": "avenue, tree-lined road",
    "senses": [
      { "gloss": "", "members": [7771, 7791] }
    ]
  },
  {
    "english": "density",
    "senses": [
      { "gloss": "", "members": [7776, 7855] }
    ]
  },
  {
    "english": "din, racket",
    "senses": [
      { "gloss": "noise, racket", "members": [7835] },
      { "gloss": "rumble, roar", "members": [7962] }
    ]
  },
  {
    "english": "tasteless",
    "senses": [
      { "gloss": "", "members": [7839, 7995] }
    ]
  },
  {
    "english": "escort",
    "senses": [
      { "gloss": "to escort", "members": [7856] },
      { "gloss": "accompanying guard", "members": [7942] }
    ]
  },
  {
    "english": "millennium",
    "senses": [
      { "gloss": "", "members": [8174, 8207] }
    ]
  },
  {
    "english": "grandson",
    "senses": [
      { "gloss": "son's son", "members": [8255] },
      { "gloss": "daughter's son", "members": [8288] }
    ]
  },
  {
    "english": "granddaughter",
    "senses": [
      { "gloss": "daughter's daughter", "members": [8267] },
      { "gloss": "son's daughter", "members": [8350] }
    ]
  }
]
